Workbook

Sheet lookupH
A1: RegNo | B1: 101 | C1: 102 | D1: 102 | E1: 102 | F1: 105 | G1: 106 | H1: 107 | I1: 108 | J1: 109 | K1: 110 | L1: 111 | M1: 112 | N1: 113 | O1: 114 | P1: 115
A2: Student Name | B2: Arjun Kumar | C2: Priya Sharma | D2: Rahul Verma | E2: Sneha Reddy | F2: Karthik Raj | G2: Ananya Singh | H2: Vishal Mehta | I2: Divya Nair | J2: Sanjay Patel | K2: Meera Iyer | L2: Rohit Das | M2: Kavya Krishna | N2: Aditya Rao | O2: Lakshmi Priya | P2: Naveen Kumar
A3: Age | B3: 19 | C3: 20 | D3: 18 | E3: 21 | F3: 19 | G3: 22 | H3: 20 | I3: 18 | J3: 21 | K3: 19 | L3: 23 | M3: 20 | N3: 22 | O3: 18 | P3: 21
A4: Location | B4: Chennai | C4: Bangalore | D4: Bangalore | E4: Coimbatore | F4: Coimbatore | G4: Coimbatore | H4: Delhi | I4: Bangalore | J4: Ahmedabad | K4: Trichy | L4: Trichy | M4: Trichy | N4: Trichy | O4: Salem | P4: Tirunelveli
A5: Fees (₹) | B5: 50000 | C5: 55000 | D5: 48000 | E5: 52000 | F5: 47000 | G5: 60000 | H5: 58000 | I5: 45000 | J5: 53000 | K5: 49000 | L5: 61000 | M5: 52000 | N5: 57000 | O5: 46000 | P5: 54000
A6: Paid (₹) | B6: 30000 | C6: 55000 | D6: 20000 | E6: 40000 | F6: 47000 | G6: 35000 | H6: 30000 | I6: 45000 | J6: 25000 | K6: 49000 | L6: 40000 | M6: 30000 | N6: 20000 | O6: 30000 | P6: 54000
A7: Balance (₹) | B7: 20000 | C7: 0 | D7: 28000 | E7: 12000 | F7: 0 | G7: 25000 | H7: 28000 | I7: 0 | J7: 28000 | K7: 0 | L7: 21000 | M7: 22000 | N7: 37000 | O7: 16000 | P7: 0
F17: Arjun Kumar | G17: =HLOOKUP(F17,B2:P7,6,FALSE) -> 20000
F18: 105

Sheet LookupV
A1: RegNo | B1: Student Name | C1: Age | D1: Location | E1: cc | F1: Paid | G1: Balance | K1: =MATCH("Paid",A1:G1) -> 6
A2: 101 | B2: Arjun Kumar | C2: 19 | D2: Chennai | E2: 50000 | F2: 30000 | G2: 20000
A3: 102 | B3: Priya Sharma | C3: 20 | D3: Bangalore | E3: 55000 | F3: 55000 | G3: 0
A4: 102 | B4: Rahul Verma | C4: 18 | D4: Bangalore | E4: 48000 | F4: 20000 | G4: 28000 | J4: Arjun Kumar | K4: =VLOOKUP(J4,B2:G16,MATCH(J10,A1:G1,),FALSE) -> 30000
A5: 102 | B5: Sneha Reddy | C5: 21 | D5: Coimbatore | E5: 52000 | F5: 40000 | G5: 12000 | J5: 104 | K5: =VLOOKUP(105,A2:G16,7,FALSE) -> 0
A6: 105 | B6: Karthik Raj | C6: 19 | D6: Coimbatore | E6: 47000 | F6: 47000 | G6: 0
A7: 106 | B7: Ananya Singh | C7: 22 | D7: Coimbatore | E7: 60000 | F7: 35000 | G7: 25000
A8: 107 | B8: Vishal Mehta | C8: 20 | D8: Delhi | E8: 58000 | F8: 30000 | G8: 28000
A9: 108 | B9: Divya Nair | C9: 18 | D9: Bangalore | E9: 45000 | F9: 45000 | G9: 0
A10: 109 | B10: Sanjay Patel | C10: 21 | D10: Ahmedabad | E10: 53000 | F10: 25000 | G10: 28000 | J10: cc
A11: 110 | B11: Meera Iyer | C11: 19 | D11: Trichy | E11: 49000 | F11: 49000 | G11: 0
A12: 111 | B12: Rohit Das | C12: 23 | D12: Trichy | E12: 61000 | F12: 40000 | G12: 21000
A13: 112 | B13: Kavya Krishna | C13: 20 | D13: Trichy | E13: 52000 | F13: 30000 | G13: 22000
A14: 113 | B14: Aditya Rao | C14: 22 | D14: Trichy | E14: 57000 | F14: 20000 | G14: 37000
A15: 114 | B15: Lakshmi Priya | C15: 18 | D15: Salem | E15: 46000 | F15: 30000 | G15: 16000
A16: 115 | B16: Naveen Kumar | C16: 21 | D16: Tirunelveli | E16: 54000 | F16: 54000 | G16: 0

Sheet Basic Math Formulas
A1: Value1 | B1: Value2 | C1: =SUM(A2:B2) | D1: =PRODUCT(A2:B2) | E1: =QUOTIENT(A2,B2) | F1: =MOD(A2,B2) | G1: =AVERAGE(A2:B2) | H1: =COUNT(A2:B2) | I1: =COUNTA(A2:B2) | J1: =LEN(A2) | K1: =POWER(A2,2) | L1: =SQRT(A2) | M1: =ROUND(L2,0) | N1: =CEILING(L2,1) | O1: =ROUNDUP(L2,0) | P1: =ROUNDDOWN(L2,0) | Q1: rand() | R1: randbetween()
A2: 333 | B2: 0 | C2: =SUM(A2:B2) -> 333 | D2: =PRODUCT(A2:B2) -> 0 | E2: =QUOTIENT(A2,B2) -> #DIV/0! | F2: =MOD(A2,B2) -> #DIV/0! | G2: =AVERAGE(A2:B2) -> 166.5 | H2: =COUNT(A2:B2) -> 2 | I2: =COUNTA(A2:B2) -> 2 | J2: =LEN(A2) -> 3 | K2: =POWER(H2,J2) -> 8 | L2: =SQRT(K2) -> 2.8284271 | M2: =ROUND(L2,0) -> 3 | N2: =CEILING(L2,1) -> 3 | O2: =ROUNDUP(L2,0) -> 3 | P2: =ROUNDDOWN(L2,0) -> 2 | Q2: =RAND() -> 0.34995559 | R2: =RANDBETWEEN(1000,9999) -> 3838
A3: 11 | B3: 2 | C3: =SUM(A3:B3) -> 13 | D3: =PRODUCT(A3:B3) -> 22 | E3: =QUOTIENT(A3,B3) -> 5 | F3: =MOD(A3,B3) -> 1 | G3: =AVERAGE(A3:B3) -> 6.5 | H3: =COUNT(A3:B3) -> 2 | I3: =COUNTA(A3:B3) -> 2 | J3: =LEN(A3) -> 2 | K3: =POWER(H3,J3) -> 4 | L3: =SQRT(K3) -> 2 | M3: =ROUND(L3,0) -> 2 | N3: =CEILING(L3,1) -> 2 | O3: =ROUNDUP(L3,0) -> 2 | P3: =ROUNDDOWN(L3,0) -> 2 | Q3: =RAND() -> 0.20688851 | R3: =RANDBETWEEN(1000,9999) -> 9953
A4: 333 | B4: 0 | C4: =SUM(A4:B4) -> 333 | D4: =PRODUCT(A4:B4) -> 0 | E4: =QUOTIENT(A4,B4) -> #DIV/0! | F4: =MOD(A4,B4) -> #DIV/0! | G4: =AVERAGE(A4:B4) -> 166.5 | H4: =COUNT(A4:B4) -> 2 | I4: =COUNTA(A4:B4) -> 2 | J4: =LEN(A4) -> 3 | K4: =POWER(H4,J4) -> 8 | L4: =SQRT(K4) -> 2.8284271 | M4: =ROUND(L4,0) -> 3 | N4: =CEILING(L4,1) -> 3 | O4: =ROUNDUP(L4,0) -> 3 | P4: =ROUNDDOWN(L4,0) -> 2 | Q4: =RAND() -> 0.3828793 | R4: =RANDBETWEEN(1000,9999) -> 6934
A5: 333 | B5: 45 | C5: =SUM(A5:B5) -> 378 | D5: =PRODUCT(A5:B5) -> 14985 | E5: =QUOTIENT(A5,B5) -> 7 | F5: =MOD(A5,B5) -> 18 | G5: =AVERAGE(A5:B5) -> 189 | H5: =COUNT(A5:B5) -> 2 | I5: =COUNTA(A5:B5) -> 2 | J5: =LEN(A5) -> 3 | K5: =POWER(H5,J5) -> 8 | L5: =SQRT(K5) -> 2.8284271 | M5: =ROUND(L5,0) -> 3 | N5: =CEILING(L5,1) -> 3 | O5: =ROUNDUP(L5,0) -> 3 | P5: =ROUNDDOWN(L5,0) -> 2 | Q5: =RAND() -> 0.45051492 | R5: =RANDBETWEEN(1000,9999) -> 4671
A6: 333 | B6: 55 | C6: =SUM(A6:B6) -> 388 | D6: =PRODUCT(A6:B6) -> 18315 | E6: =QUOTIENT(A6,B6) -> 6 | F6: =MOD(A6,B6) -> 3 | G6: =AVERAGE(A6:B6) -> 194 | H6: =COUNT(A6:B6) -> 2 | I6: =COUNTA(A6:B6) -> 2 | J6: =LEN(A6) -> 3 | K6: =POWER(H6,J6) -> 8 | L6: =SQRT(K6) -> 2.8284271 | M6: =ROUND(L6,0) -> 3 | N6: =CEILING(L6,1) -> 3 | O6: =ROUNDUP(L6,0) -> 3 | P6: =ROUNDDOWN(L6,0) -> 2 | Q6: =RAND() -> 0.31399392 | R6: =RANDBETWEEN(1000,9999) -> 8224
A7: 333 | B7: 65 | C7: =SUM(A7:B7) -> 398 | D7: =PRODUCT(A7:B7) -> 21645 | E7: =QUOTIENT(A7,B7) -> 5 | F7: =MOD(A7,B7) -> 8 | G7: =AVERAGE(A7:B7) -> 199 | H7: =COUNT(A7:B7) -> 2 | I7: =COUNTA(A7:B7) -> 2 | J7: =LEN(A7) -> 3 | K7: =POWER(H7,J7) -> 8 | L7: =SQRT(K7) -> 2.8284271 | M7: =ROUND(L7,0) -> 3 | N7: =CEILING(L7,1) -> 3 | O7: =ROUNDUP(L7,0) -> 3 | P7: =ROUNDDOWN(L7,0) -> 2 | Q7: =RAND() -> 0.0027709531 | R7: =RANDBETWEEN(1000,9999) -> 6065
A8: 333 | B8: 75 | C8: =SUM(A8:B8) -> 408 | D8: =PRODUCT(A8:B8) -> 24975 | E8: =QUOTIENT(A8,B8) -> 4 | F8: =MOD(A8,B8) -> 33 | G8: =AVERAGE(A8:B8) -> 204 | H8: =COUNT(A8:B8) -> 2 | I8: =COUNTA(A8:B8) -> 2 | J8: =LEN(A8) -> 3 | K8: =POWER(H8,J8) -> 8 | L8: =SQRT(K8) -> 2.8284271 | M8: =ROUND(L8,0) -> 3 | N8: =CEILING(L8,1) -> 3 | O8: =ROUNDUP(L8,0) -> 3 | P8: =ROUNDDOWN(L8,0) -> 2 | Q8: =RAND() -> 0.3899019 | R8: =RANDBETWEEN(1000,9999) -> 7650
A9: 333 | B9: 85 | C9: =SUM(A9:B9) -> 418 | D9: =PRODUCT(A9:B9) -> 28305 | E9: =QUOTIENT(A9,B9) -> 3 | F9: =MOD(A9,B9) -> 78 | G9: =AVERAGE(A9:B9) -> 209 | H9: =COUNT(A9:B9) -> 2 | I9: =COUNTA(A9:B9) -> 2 | J9: =LEN(A9) -> 3 | K9: =POWER(H9,J9) -> 8 | L9: =SQRT(K9) -> 2.8284271 | M9: =ROUND(L9,0) -> 3 | N9: =CEILING(L9,1) -> 3 | O9: =ROUNDUP(L9,0) -> 3 | P9: =ROUNDDOWN(L9,0) -> 2 | Q9: =RAND() -> 0.63928788 | R9: =RANDBETWEEN(1000,9999) -> 6435
A10: text | B10: 22 | C10: =SUM(A10:B10) -> 22 | D10: =PRODUCT(A10:B10) -> 22 | E10: =QUOTIENT(A10,B10) -> #VALUE! | F10: =MOD(A10,B10) -> #VALUE! | G10: =AVERAGE(A10:B10) -> 22 | H10: =COUNT(A10:B10) -> 1 | I10: =COUNTA(A10:B10) -> 2 | J10: =LEN(A10) -> 4 | K10: =POWER(H10,J10) -> 1 | L10: =SQRT(K10) -> 1 | M10: =ROUND(L10,0) -> 1 | N10: =CEILING(L10,1) -> 1 | O10: =ROUNDUP(L10,0) -> 1 | P10: =ROUNDDOWN(L10,0) -> 1 | Q10: =RAND() -> 0.021642462 | R10: =RANDBETWEEN(1000,9999) -> 1688

Sheet date and Time Functions
A1: Date and Time Functions
G2: TODAY(), NOW(), DATE(), TIME(), DATEDIF(), YEAR(), MONTH(), DAY(), HOUR(), MINUTE(), SECOND()
D4: =DATE(2022,7,22) | E4: =TODAY() | F4: =YEAR(E6) | G4: =MONTH(E6) | H4: =DAY(E6) | J4: =DATEDIF(D6,E6,"Y") | K4: =DATEDIF(D6,E6,"M") | L4: =DATEDIF(D6,E6,"D")
D6: =DATE(2022,7,22) -> 44764 | E6: =TODAY() -> 46086 | F6: =YEAR(D6) -> 2022 | G6: =MONTH(D6) -> 7 | H6: =DAY(D6) -> 22 | J6: =DATEDIF(D6,E6,"Y") -> 3 | K6: =DATEDIF(D6,E6,"M") -> 43 | L6: =DATEDIF(D6,E6,"D") -> 1322
B9: =NOW()
B10: =NOW() -> 46086.533
D14: =TIME(2,30,30) | E14: =HOUR(D16) | F14: =MINUTE(D16) | G14: =SECOND(D16)
D16: =TIME(2,30,30) -> 0.10451389 | E16: =HOUR(D16) -> 2 | F16: =MINUTE(D16) -> 30 | G16: =SECOND(D16) -> 30

Sheet Text Functins
A1: Text Functions
A2: CONCATENATE(), TEXT(), LEFT(), RIGHT(), MID(), LEN(), TRIM(), UPPER(), LOWER(), PROPER(), REPT(), SUBSTITUTE(), FIND(), SEARCH()
A3: Invoice ID | B3: Branch | C3: City | D3: Customer type | E3: Gender | F3: Product line | G3: Unit price | H3: Quantity | I3: Tax 5% | J3: Total | K3: =CONCATENATE(C4,"_",D4) | L3: =TEXT(J4,"#,##0") =TEXT(O9,"MM/DD/YYYY") | M3: =LEFT(K4,5) | N3: =RIGHT(K4,6) | O3: =MID(K4,5,8) | P3: =LEN(F4) | Q3: =TRIM(F4) | S3: =UPPER(K4) | T3: =LOWER(S4) | U3: =PROPER(T4) | V3: =REPT(P4,5) | W3: =SUBSTITUTE(U4,"Trichy","Chennai") | X3: =FIND("em",U4) | Y3: =SEARCH("em",T4) | Z3: Customer ID creation Randomly =UPPER(CONCATENATE("CUST",LEFT(A4,2),"BR",B4,"LOC",LEFT(C4,3),RANDBETWEEN(1000,9999)))
A4: 750-67-8428 | B4: A | C4: Trichy | D4: Member | E4: Female | F4: Health and beauty | G4: 74.69 | H4: 7 | I4: 26.1415 | J4: 20000000 | K4: =CONCATENATE(C4,"_",D4) -> Trichy_Member | L4: =TEXT(J4,"#,##0") -> 2,00,00,000 | M4: =LEFT(K4,5) -> Trich | N4: =RIGHT(K4,6) -> Member | O4: =MID(K4,5,8) -> hy_Membe | P4: =LEN(F4) -> 19 | Q4: =TRIM(F4) -> Health and beauty | S4: =UPPER(K4) -> TRICHY_MEMBER | T4: =LOWER(S4) -> trichy_member | U4: =PROPER(T4) -> Trichy_Member | V4: =REPT(P4,5) -> 1919191919 | W4: =SUBSTITUTE(U4,"Trichy","Chennai") -> Chennai_Member | X4: =FIND("em",U4) -> 9 | Y4: =SEARCH("em",T4) -> 9 | Z4: =UPPER(CONCATENATE("CUST",LEFT(A4,2),"BR",B4,"LOC",LEFT(C4,3),RANDBETWEEN(1000,9999))) -> CUST75BRALOCTRI1423
A5: 226-31-3081 | B5: C | C5: Chennai | D5: Normal | E5: Female | F5: Electronic accessories | G5: 15.28 | H5: 5 | I5: 3.82 | J5: 80.22 | K5: =CONCATENATE(C5,"_",D5) -> Chennai_Normal | M5: =LEFT(K5,5) -> Chenn | N5: =RIGHT(K5,6) -> Normal | P5: =LEN(Q4) -> 17 | Z5: =UPPER(CONCATENATE("CUST",LEFT(A5,2),"BR",B5,"LOC",LEFT(C5,3),RANDBETWEEN(1000,9999))) -> CUST22BRCLOCCHE3507
A6: 631-41-3108 | B6: A | C6: Trichy | D6: Normal | E6: Male | F6: Home and lifestyle | G6: 46.33 | H6: 7 | I6: 16.2155 | J6: 340.5255 | K6: =CONCATENATE(C6,"_",D6) -> Trichy_Normal | M6: =LEFT(K6,5) -> Trich | N6: =RIGHT(K6,6) -> Normal | Z6: =UPPER(CONCATENATE("CUST",LEFT(A6,2),"BR",B6,"LOC",LEFT(C6,3),RANDBETWEEN(1000,9999))) -> CUST63BRALOCTRI5621
A7: 123-19-1176 | B7: A | C7: Trichy | D7: Member | E7: Male | F7: Health and beauty | G7: 58.22 | H7: 8 | I7: 23.288 | J7: 489.048 | K7: =CONCATENATE(C7,"_",D7) -> Trichy_Member | M7: =LEFT(K7,5) -> Trich | N7: =RIGHT(K7,6) -> Member | Z7: =UPPER(CONCATENATE("CUST",LEFT(A7,2),"BR",B7,"LOC",LEFT(C7,3),RANDBETWEEN(1000,9999))) -> CUST12BRALOCTRI1556
A8: 373-73-7910 | B8: A | C8: Trichy | D8: Normal | E8: Male | F8: Sports and travel | G8: 86.31 | H8: 7 | I8: 30.2085 | J8: 634.3785 | K8: =CONCATENATE(C8,"_",D8) -> Trichy_Normal | M8: =LEFT(K8,5) -> Trich | N8: =RIGHT(K8,6) -> Normal | Z8: =UPPER(CONCATENATE("CUST",LEFT(A8,2),"BR",B8,"LOC",LEFT(C8,3),RANDBETWEEN(1000,9999))) -> CUST37BRALOCTRI9143
A9: 699-14-3026 | B9: C | C9: Chennai | D9: Normal | E9: Male | F9: Electronic accessories | G9: 85.39 | H9: 7 | I9: 29.8865 | J9: 627.6165 | K9: =CONCATENATE(C9,"_",D9) -> Chennai_Normal | L9: =TEXT(O9,"MM/DD/YYYY") -> 07/23/2025 | M9: =LEFT(K9,5) -> Chenn | N9: =RIGHT(K9,6) -> Normal | O9: 45861 | Z9: =UPPER(CONCATENATE("CUST",LEFT(A9,2),"BR",B9,"LOC",LEFT(C9,3),RANDBETWEEN(1000,9999))) -> CUST69BRCLOCCHE7103
A10: 355-53-5943 | B10: A | C10: Trichy | D10: Member | E10: Female | F10: Electronic accessories | G10: 68.84 | H10: 6 | I10: 20.652 | J10: 433.692 | K10: =CONCATENATE(C10,"_",D10) -> Trichy_Member | M10: =LEFT(K10,5) -> Trich | N10: =RIGHT(K10,6) -> Member | Z10: =UPPER(CONCATENATE("CUST",LEFT(A10,2),"BR",B10,"LOC",LEFT(C10,3),RANDBETWEEN(1000,9999))) -> CUST35BRALOCTRI7241
A11: 315-22-5665 | B11: C | C11: Chennai | D11: Normal | E11: Female | F11: Home and lifestyle | G11: 73.56 | H11: 10 | I11: 36.78 | J11: 772.38 | K11: =CONCATENATE(C11,"_",D11) -> Chennai_Normal | M11: =LEFT(K11,5) -> Chenn | N11: =RIGHT(K11,6) -> Normal | Z11: =UPPER(CONCATENATE("CUST",LEFT(A11,2),"BR",B11,"LOC",LEFT(C11,3),RANDBETWEEN(1000,9999))) -> CUST31BRCLOCCHE2748
A12: 665-32-9167 | B12: A | C12: Trichy | D12: Member | E12: Female | F12: Health and beauty | G12: 36.26 | H12: 2 | I12: 3.626 | J12: 76.146 | K12: =CONCATENATE(C12,"_",D12) -> Trichy_Member | M12: =LEFT(K12,5) -> Trich | N12: =RIGHT(K12,6) -> Member | Z12: =UPPER(CONCATENATE("CUST",LEFT(A12,2),"BR",B12,"LOC",LEFT(C12,3),RANDBETWEEN(1000,9999))) -> CUST66BRALOCTRI1382
A13: 692-92-5582 | B13: B | C13: karur | D13: Member | E13: Female | F13: Food and beverages | G13: 54.84 | H13: 3 | I13: 8.226 | J13: 172.746 | K13: =CONCATENATE(C13,"_",D13) -> karur_Member | M13: =LEFT(K13,5) -> karur | N13: =RIGHT(K13,6) -> Member | Z13: =UPPER(CONCATENATE("CUST",LEFT(A13,2),"BR",B13,"LOC",LEFT(C13,3),RANDBETWEEN(1000,9999))) -> CUST69BRBLOCKAR3086
A14: 351-62-0822 | B14: B | C14: karur | D14: Member | E14: Female | F14: Fashion accessories | G14: 14.48 | H14: 4 | I14: 2.896 | J14: 60.816 | K14: =CONCATENATE(C14,"_",D14) -> karur_Member | M14: =LEFT(K14,5) -> karur | N14: =RIGHT(K14,6) -> Member | Z14: =UPPER(CONCATENATE("CUST",LEFT(A14,2),"BR",B14,"LOC",LEFT(C14,3),RANDBETWEEN(1000,9999))) -> CUST35BRBLOCKAR8641
A15: 529-56-3974 | B15: B | C15: karur | D15: Member | E15: Male | F15: Electronic accessories | G15: 25.51 | H15: 4 | I15: 5.102 | J15: 107.142 | K15: =CONCATENATE(C15,"_",D15) -> karur_Member | M15: =LEFT(K15,5) -> karur | N15: =RIGHT(K15,6) -> Member | Z15: =UPPER(CONCATENATE("CUST",LEFT(A15,2),"BR",B15,"LOC",LEFT(C15,3),RANDBETWEEN(1000,9999))) -> CUST52BRBLOCKAR4282
A16: 365-64-0515 | B16: A | C16: Trichy | D16: Normal | E16: Female | F16: Electronic accessories | G16: 46.95 | H16: 5 | I16: 11.7375 | J16: 246.4875 | K16: =CONCATENATE(C16,"_",D16) -> Trichy_Normal | M16: =LEFT(K16,5) -> Trich | N16: =RIGHT(K16,6) -> Normal | Z16: =UPPER(CONCATENATE("CUST",LEFT(A16,2),"BR",B16,"LOC",LEFT(C16,3),RANDBETWEEN(1000,9999))) -> CUST36BRALOCTRI1614
A17: 252-56-2699 | B17: A | C17: Trichy | D17: Normal | E17: Male | F17: Food and beverages | G17: 43.19 | H17: 10 | I17: 21.595 | J17: 453.495 | K17: =CONCATENATE(C17,"_",D17) -> Trichy_Normal | M17: =LEFT(K17,5) -> Trich | N17: =RIGHT(K17,6) -> Normal | Z17: =UPPER(CONCATENATE("CUST",LEFT(A17,2),"BR",B17,"LOC",LEFT(C17,3),RANDBETWEEN(1000,9999))) -> CUST25BRALOCTRI7696
A18: 829-34-3910 | B18: A | C18: Trichy | D18: Normal | E18: Female | F18: Health and beauty | G18: 71.38 | H18: 10 | I18: 35.69 | J18: 749.49 | K18: =CONCATENATE(C18,"_",D18) -> Trichy_Normal | M18: =LEFT(K18,5) -> Trich | N18: =RIGHT(K18,6) -> Normal | Z18: =UPPER(CONCATENATE("CUST",LEFT(A18,2),"BR",B18,"LOC",LEFT(C18,3),RANDBETWEEN(1000,9999))) -> CUST82BRALOCTRI8728
A19: 299-46-1805 | B19: B | C19: karur | D19: Member | E19: Female | F19: Sports and travel | G19: 93.72 | H19: 6 | I19: 28.116 | J19: 590.436 | K19: =CONCATENATE(C19,"_",D19) -> karur_Member | M19: =LEFT(K19,5) -> karur | N19: =RIGHT(K19,6) -> Member | Z19: =UPPER(CONCATENATE("CUST",LEFT(A19,2),"BR",B19,"LOC",LEFT(C19,3),RANDBETWEEN(1000,9999))) -> CUST29BRBLOCKAR6855
A20: 656-95-9349 | B20: A | C20: Trichy | D20: Member | E20: Female | F20: Health and beauty | G20: 68.93 | H20: 7 | I20: 24.1255 | J20: 506.6355 | K20: =CONCATENATE(C20,"_",D20) -> Trichy_Member | M20: =LEFT(K20,5) -> Trich | N20: =RIGHT(K20,6) -> Member | Z20: =UPPER(CONCATENATE("CUST",LEFT(A20,2),"BR",B20,"LOC",LEFT(C20,3),RANDBETWEEN(1000,9999))) -> CUST65BRALOCTRI7510
A21: 765-26-6951 | B21: A | C21: Trichy | D21: Normal | E21: Male | F21: Sports and travel | G21: 72.61 | H21: 6 | I21: 21.783 | J21: 457.443 | K21: =CONCATENATE(C21,"_",D21) -> Trichy_Normal | M21: =LEFT(K21,5) -> Trich | N21: =RIGHT(K21,6) -> Normal | Z21: =UPPER(CONCATENATE("CUST",LEFT(A21,2),"BR",B21,"LOC",LEFT(C21,3),RANDBETWEEN(1000,9999))) -> CUST76BRALOCTRI1286
... A34: 871-79-8483 | B34: B | C34: karur | D34: Normal | E34: Male | F34: Fashion accessories | G34: 94.13 | H34: 5 | I34: 23.5325 | J34: 494.1825 | K34: =CONCATENATE(C34,"_",D34) -> karur_Normal | M34: =LEFT(K34,5) -> karur | N34: =RIGHT(K34,6) -> Normal | Z34: =UPPER(CONCATENATE("CUST",LEFT(A34,2),"BR",B34,"LOC",LEFT(C34,3),RANDBETWEEN(1000,9999))) -> CUST87BRBLOCKAR6447

Sheet Logical Functions
A1: id | C1: fees | D1: course | E1: IF | F1: AND | G1: OR | I1: NOT | J1: IFERROR | K1: IFS | L1: SWITCH | M1: XOR | N1: FALSE | O1: TRUE | Q1: SUMIF() | T1: Function Name | U1: Description
B2: name | E2: Returns "Greater than 20" if Value1 > 20, otherwise "Less or equal to 20" | F2: Returns TRUE if Value1 > 10 and Value2 < 30 | G2: Returns TRUE if Value1 > 10 or Value2 < 30 | H2: Returns TRUE if Value1 > 10 AND Value2 < 30 | I2: Returns TRUE if Value1 is not greater than 15 | J2: Returns "Error" if dividing Value1 by Value2 results in an error | K2: Evaluates multiple conditions and returns the corresponding value | L2: Returns corresponding category name based on Category value | M2: Returns TRUE if exactly one of the conditions is TRUE | N2: Returns the logical value FALSE | O2: Returns the logical value TRUE | T2: IF | U2: Returns "Greater than 20" if Value1 > 20, otherwise "Less or equal to 20"
E3: =IF(A2>20, "Greater than 20", "Less or equal to 20") | F3: =AND(A2>10, B2<30) | G3: =OR(A3>10, B3<30) | H3: =AND(A4>10, B4<30) | I3: =NOT(a3>15) | J3: =IFERROR(A3/A3, "Error") | K3: =IFS(D1>30, "Above 30", D1>20, "Above 20", D1>10, "Above 10") | L3: =_xlfn.SWITCH(F6, "A", "Category A", "B", "Category B", "Unknown") | M3: =XOR(D1>10, F5<30) | N3: =FALSE() | O3: =TRUE() | P3: =IF(A4>0,"A value is greater than zero", "A value is no greater") | Q3: =SUMIF(C4:C8,"A",A4:A8) | R3: =SUMIFS(A4:A8,C4:C8,"A",B4:B8,0) | T3: AND | U3: Returns TRUE if Value1 > 10 and Value2 < 30
A4: 40 | B4: ragu | C4: 33300 | D4: java | E4: =IF(B4="ravi","this is ravi","this is not ravi") -> this is not ravi | G4: =OR(A4>10, C4<30) -> TRUE | H4: =AND(A4>10, C4<30) -> FALSE | I4: =NOT(A4>15) -> FALSE | J4: =IFERROR(22/"x","cannot divide by letters") -> cannot divide by letters | K4: =IFS(A4>30, "Above 30", C4>20, "Above 20", A5>10, "Above 10") -> #NAME? | L4: =_xlfn.SWITCH("A", "A", "Category A", "B", "Category B", "Unknown") -> #NAME? | M4: =_xludf.XOR(E3>10, G6<30) -> #NAME? | N4: =FALSE() -> FALSE | O4: =TRUE() -> TRUE | P4: =IF(A4>0,"A value is greater than zero", "A value is no greater") -> A value is greater than zero | Q4: =SUMIF(D4:D8,"A",A4:A8) -> 0 | R4: =SUMIFS(A4:A8,D4:D8,"A",C4:C8,0) -> 0 | T4: OR | U4: Returns TRUE if Value1 > 10 or Value2 < 30
A5: 55 | B5: ravi | C5: 2000 | D5: python | E5: =IF(C5>25000,"paid above 25000rs", "not paid above 25000rs") -> not paid above 25000rs | F5: =IF(AND(B5="ravi",C5>25000),"yes he is raju and he paid above 25000rs", "no he is not") -> no he is not | G5: =IF(OR(C5="ravi",D5>25000),"yes he is raju and he paid above 25000rs", "no he is not") -> yes he is raju and he paid above 25000rs | I5: =IF(NOT(AND(E5="ravi",F5>25000)),"yes he is raju and he paid above 25000rs", "no he is not") -> yes he is raju and he paid above 25000rs | J5: =IFERROR(A5/C5, "Error") -> 0.0275 | P5: =IF(A5>30,"A value is greater than given", "A value is no greater than given") -> A value is greater than given | Q5: =SUMIF(D5:D9,"A",A5:A9) -> 0 | R5: =SUMIFS(A5:A9,D5:D9,"A",C5:C9,0) -> 0 | T5: NOT | U5: Returns TRUE if Value1 is not greater than 15
A6: 30 | B6: raju | C6: 23400 | D6: java | E6: =IF(B6="raju",CONCATENATE("raju : ",C6),IF(B6="ragav",CONCATENATE("Ragav : ",C6),IF(B6="ram",CONCATENATE("Ram : ",C6),B6))) -> raju : 23400 | G6: =OR(A6>10, C6<30) -> TRUE | J6: =IFERROR(A6/C6, "Error") -> 0.0012820513 | P6: =IF(A6>0,D6, "A value is no greater than given") -> java | Q6: =SUMIF(D6:D10,"A",A6:A10) -> 0 | R6: =SUMIFS(A6:A10,D6:D10,"A",C6:C10,0) -> 0 | T6: IFERROR | U6: Returns "Error" if dividing Value1 by Value2 results in an error
A7: 40 | B7: ram | C7: 24570 | D7: python | E7: =IF(B7="raju",CONCATENATE("raju : ",C7),IF(B7="ragav",CONCATENATE("Ragav : ",C7),IF(B7="ram",CONCATENATE("Ram : ",C7),B7))) -> Ram : 24570 | G7: =OR(A7>10, C7<30) -> TRUE | J7: =IFERROR(A7/C7, "Error") -> 0.0016280016 | Q7: =SUMIF(D7:D11,"A",B7:B11) -> 0 | R7: =SUMIFS(B7:B11,D7:D11,"A",C7:C11,0) -> 0 | T7: IFS | U7: Evaluates multiple conditions and returns the corresponding value
A8: 50 | B8: ragav | C8: 33300 | D8: java | E8: =IF(B8="raju",CONCATENATE("raju : ",C8),IF(B8="ragav",CONCATENATE("Ragav : ",C8),IF(B8="ram",CONCATENATE("Ram : ",C8),B8))) -> Ragav : 33300 | G8: =OR(A8>10, C8<30) -> TRUE | J8: =IFERROR(A8/C8, "Error") -> 0.0015015015 | Q8: =SUMIF(D8:D12,"A",B8:B12) -> 0 | R8: =SUMIFS(B8:B12,D8:D12,"A",C8:C12,0) -> 0 | T8: SWITCH | U8: Returns corresponding category name based on Category value
T9: XOR | U9: Returns TRUE if exactly one of the conditions is TRUE
T10: FALSE | U10: Returns the logical value FALSE
T11: TRUE | U11: Returns the logical value TRUE
E13: =CONCATENATE(C8," ",D8," ",B8) -> 33300 java ragav
U14: =FALSE -> FALSE

Sheet Statistical Functions
A1: Statistical Functions
A2: Value1 | B2: Value2 | C2: Category | E2: AVERAGE(), MEDIAN(), MODE(), COUNT(), COUNTA(), COUNTIF(), COUNTIFS(), MAX(), MIN(), STDEV(), VAR()
D4: =AVERAGE(A5:A9) | E4: =MEDIAN(A5:A9) | F4: =MODE(A5:A9) | G4: =COUNT(A5:A9) | H4: =COUNTA(C5:C9) | I4: =COUNTIF(C5:C9,"A") | J4: =COUNTIFS(C5:C9,"A",B5:B9,0) | K4: =MAX(B5:B9) | L4: =MIN(B5:B9) | M4: =STDEV(A5:A9) | N4: =VAR(A5:A9)
A5: 44 | B5: 0 | C5: A | D5: =AVERAGE(A5:A9) -> 35.6 | E5: =MEDIAN(A5:A9) -> 30 | F5: =MODE(A5:A9) -> 30 | G5: =COUNT(A5:A9) -> 5 | H5: =COUNTA(C5:C9) -> 5 | I5: =COUNTIF(C5:C9,"A") -> 3 | J5: =COUNTIFS(C5:C9,"A",B5:B9,0) -> 2 | K5: =MAX(B5:B9) -> 55 | L5: =MIN(B5:B9) -> 0 | M5: =STDEV(A5:A9) -> 7.6681158 | N5: =VAR(A5:A9) -> 58.8
A6: 30 | B6: 25 | C6: B | D6: =AVERAGE(A6:A10) -> 33.5 | E6: =MEDIAN(A6:A10) -> 30 | F6: =MODE(A5:A10) -> 30 | G6: =COUNT(A6:A10) -> 4
A7: 30 | B7: 0 | C7: A | D7: =AVERAGE(A7:A11) -> 34.666667 | E7: =MEDIAN(A7:A11) -> 30 | G7: =COUNT(A7:A11) -> 3
A8: 30 | B8: 45 | C8: B | D8: =AVERAGE(A8:A12) -> 37 | E8: =MEDIAN(A8:A12) -> 37 | G8: =COUNT(A8:A12) -> 2
A9: 44 | B9: 55 | C9: A | D9: =AVERAGE(A9:A13) -> 44 | E9: =MEDIAN(A9:A13) -> 44 | G9: =COUNT(A9:A13) -> 1
N11: =SQRT(N5) -> 7.6681158
H15: mode()
A16: dataset original | C16: 1 | D16: 3 | E16: 4 | F16: 5 | G16: 3 | H16: =MEDIAN(C16:G16) -> 3
A17: asending order | C17: 1 | D17: 3 | E17: 3 | F17: 4 | G17: 5 | H17: 3 | I17: after asending pick center value

Sheet Lookup (V and H _Lookup) 
B1: Lookup (V-Lookup and H-Lookup)
A2: Category | B2: Value1 | C2: Fees Pending | D2: VLOOKUP(), HLOOKUP(), LOOKUP()
A5: A | B5: 40 | C5: 0
A6: B | B6: 55 | C6: 55 | G6: value2 | H6: =VLOOKUP(G7,A5:F26,2)
A7: E | B7: 30 | C7: 0 | G7: A | H7: =VLOOKUP(G7,A5:F9,3) -> 0
A8: F | B8: 40 | C8: 45 | D8: fsd | E8: 33 | F8: 333 | G8: B | H8: =VLOOKUP(G8,A5:F9,3) -> 55
A9: D | B9: 50 | C9: 55 | G9: D | H9: =VLOOKUP(G9,A5:F9,3) -> 55
H15: Exact Match (False)
A16: Category | B16: A | C16: B | D16: E | E16: F | F16: D | G16: value2 | H16: =HLOOKUP(G7,A16:F26,2,)
A17: Value1 | B17: 40 | C17: 55 | D17: 30 | E17: 40 | F17: 50 | G17: d | H17: =HLOOKUP(G17,A16:F26,2,) -> 50
A18: Fees Pending | B18: 0 | C18: 25 | D18: 0 | E18: 45 | F18: 55 | G18: 50 | H18: =HLOOKUP(G18,B17:F21,2,TRUE) -> 55
E19: fsd
E20: 33
E21: 333

Sheet Reference Functions
C1: Reference Functions
D2: INDEX(), MATCH(), INDIRECT(), OFFSET(), CHOOSE(), ROW(), COLUMN()
A3: A | B3: B | C3: C | D3: =INDEX(B2:B4, 2) | E3: =MATCH("Sarah", A2:A4, 0) | F3: =INDIRECT("B2") | G3: =OFFSET(B2, 1, 0) | H3: =CHOOSE(2, "Red", "Green", "Blue") | I3: =ROW(A3) | J3: =COLUMN(B2)
A4: Name | B4: Age | C4: Gender
A5: John | B5: 25 | C5: Male | D5: =INDEX(A4:C21, 3,2) -> 30 | E5: =MATCH("Sarah", A4:A7, 0) -> 3 | F5: =INDIRECT("B5") -> 25 | G5: =OFFSET(B5, 2, 1) -> male | H5: =CHOOSE(2, A5,A6,A7) -> Sarah | I5: =ROW(C7) -> 7 | J5: =COLUMN(C7) -> 3
A6: Sarah | B6: 30 | C6: Female | E6: =MATCH(27, B4:B7, 1) -> 2 | F6: =B5 -> 25
A7: Mike | B7: 35 | C7: male
D15: =A5 -> John

Sheet Sheet1
A1: ='Reference Functions'!A4 -> Name | B1: ='Reference Functions'!C4 -> Gender
A2: ='Reference Functions'!A5 -> John | B2: ='Reference Functions'!C5 -> Male
A3: ='Reference Functions'!A6 -> Sarah | B3: ='Reference Functions'!C6 -> Female
A4: ='Reference Functions'!A7 -> Mike | B4: ='Reference Functions'!C7 -> male
A5: ='Reference Functions'!A8 -> 0 | B5: ='Reference Functions'!C8 -> 0
A6: ='Reference Functions'!A9 -> 0 | B6: ='Reference Functions'!C9 -> 0
A7: ='Reference Functions'!A10 -> 0 | B7: ='Reference Functions'!C10 -> 0
A8: ='Reference Functions'!A11 -> 0 | B8: ='Reference Functions'!C11 -> 0
A9: ='Reference Functions'!A12 -> 0 | B9: ='Reference Functions'!C12 -> 0
A10: ='Reference Functions'!A13 -> 0 | B10: ='Reference Functions'!C13 -> 0
A11: ='Reference Functions'!A14 -> 0 | B11: ='Reference Functions'!C14 -> 0
